<annotation verified="yes">
    <folder>Annotation</folder>
    <filename>IMG_20210329_204610_1.jpg</filename>
    <path>fw2_3_26-PascalVOC-export/Annotations/IMG_20210329_204610_1.jpg</path>
    <source>
        <database>Unknown</database>
    </source>
    <size>
        <width>800</width>
        <height>800</height>
        <depth>3</depth>
    </size>
    <segmented>0</segmented>
    <object>
    <name>spitball</name>
    <pose>Unspecified</pose>
    <truncated>0</truncated>
    <difficult>0</difficult>
    <bndbox>
        <xmin>266.45962732919253</xmin>
        <ymin>3.105590062111801</ymin>
        <xmax>563.3540372670807</xmax>
        <ymax>515.5279503105589</ymax>
    </bndbox>
</object>
</annotation>
