<annotation verified="yes">
    <folder>Annotation</folder>
    <filename>IMG_20210402_160446.jpg</filename>
    <path>fw2_3_26-PascalVOC-export/Annotations/IMG_20210402_160446.jpg</path>
    <source>
        <database>Unknown</database>
    </source>
    <size>
        <width>800</width>
        <height>800</height>
        <depth>3</depth>
    </size>
    <segmented>0</segmented>
    <object>
    <name>boxes</name>
    <pose>Unspecified</pose>
    <truncated>0</truncated>
    <difficult>0</difficult>
    <bndbox>
        <xmin>119.87577639751552</xmin>
        <ymin>167.70186335403724</ymin>
        <xmax>800</xmax>
        <ymax>800</ymax>
    </bndbox>
</object>
</annotation>
